changelog2version/__init__.py
changelog2version/extract_version.py
changelog2version/render_version_file.py
changelog2version/update_version.py
changelog2version/version.py
changelog2version/templates/version.h.template
changelog2version/templates/version.py.template
changelog2version-0.12.1.dist-info/LICENSE.txt
changelog2version-0.12.1.dist-info/METADATA
changelog2version-0.12.1.dist-info/WHEEL
changelog2version-0.12.1.dist-info/entry_points.txt
changelog2version-0.12.1.dist-info/top_level.txt
changelog2version-0.12.1.dist-info/RECORD
