Metadata-Version: 2.1
Name: changelog2version
Version: 0.12.1
Summary: Update version info file with latest changelog version entry
Home-page: https://github.com/brainelectronics/changelog2version
Author: brainelectronics
Author-email: info@brainelectronics.de
Project-URL: Bug Reports, https://github.com/brainelectronics/changelog2version/issues
Project-URL: Source, https://github.com/brainelectronics/changelog2version/
Keywords: changelog,version,changelog-parser,versioning,extract
Classifier: Development Status :: 5 - Production/Stable
Classifier: Intended Audience :: Developers
Classifier: Topic :: Software Development :: Build Tools
Classifier: License :: OSI Approved :: MIT License
Classifier: Programming Language :: Python :: 3
Classifier: Programming Language :: Python :: 3.9
Classifier: Programming Language :: Python :: 3.10
Classifier: Programming Language :: Python :: 3.11
Classifier: Programming Language :: Python :: 3 :: Only
Requires-Python: >=3.7, <4
License-File: LICENSE.txt
Requires-Dist: semver<3,>=2.13.0
Requires-Dist: jinja2<4,>=3.1.0
Provides-Extra: dev
Requires-Dist: tox<4,>=3.25.1; extra == "dev"
Provides-Extra: test
Requires-Dist: flake8<6,>=5.0.0; extra == "test"
Requires-Dist: coverage<7,>=6.4.2; extra == "test"
Requires-Dist: nose2<1,>=0.12.0; extra == "test"
